{"chunk_definitions":[{"row":55,"row_count":1,"visible":true,"expansion_state":0,"options":{"engine":"r","label":"setup","include":false,"dev":"png"},"document_id":"597FF5A4","chunk_id":"csetup_chunk","chunk_label":"setup"},{"row":72,"row_count":1,"visible":true,"expansion_state":0,"options":{},"document_id":"597FF5A4","chunk_id":"cgnoldsh5x62r","chunk_label":"libraries"},{"row":147,"row_count":1,"visible":true,"expansion_state":0,"options":{},"document_id":"597FF5A4","chunk_id":"c5su7mfbn69ok","chunk_label":"load-data"},{"row":195,"row_count":1,"visible":true,"expansion_state":0,"options":{},"document_id":"597FF5A4","chunk_id":"cx5pzi1ivbjcz","chunk_label":"helpers"},{"row":218,"row_count":1,"visible":true,"expansion_state":0,"options":{},"document_id":"597FF5A4","chunk_id":"c2hqmuhg7yhu4","chunk_label":"data-quality-checks"},{"row":246,"row_count":1,"visible":true,"expansion_state":0,"options":{},"document_id":"597FF5A4","chunk_id":"c4ciwf6kfj4dh","chunk_label":"missing-data-analysis"},{"row":275,"row_count":1,"visible":true,"expansion_state":0,"options":{},"document_id":"597FF5A4","chunk_id":"crq1n4avxwgyq","chunk_label":"numeric-range-checks"},{"row":296,"row_count":1,"visible":true,"expansion_state":0,"options":{},"document_id":"597FF5A4","chunk_id":"cmxhcpboubeid","chunk_label":"tenure-classification-check"},{"row":313,"row_count":1,"visible":true,"expansion_state":0,"options":{},"document_id":"597FF5A4","chunk_id":"c2cb75t2g2z3s","chunk_label":"salary-table-cell-sizes"},{"row":327,"row_count":1,"visible":true,"expansion_state":0,"options":{},"document_id":"597FF5A4","chunk_id":"c8gkee4k14sdb","chunk_label":"membership"},{"row":346,"row_count":1,"visible":true,"expansion_state":0,"options":{},"document_id":"597FF5A4","chunk_id":"cva7mr55xm642","chunk_label":"degree"},{"row":365,"row_count":1,"visible":true,"expansion_state":0,"options":{},"document_id":"597FF5A4","chunk_id":"cmzw8n988g436","chunk_label":"degree-area"},{"row":387,"row_count":1,"visible":true,"expansion_state":0,"options":{},"document_id":"597FF5A4","chunk_id":"cinq2je4ts7ag","chunk_label":"role-duration"},{"row":411,"row_count":1,"visible":true,"expansion_state":0,"options":{},"document_id":"597FF5A4","chunk_id":"cuir654ad2mem","chunk_label":"rank-tenure"},{"row":430,"row_count":1,"visible":true,"expansion_state":0,"options":{},"document_id":"597FF5A4","chunk_id":"c2kpzd1wr4apy","chunk_label":"supervisor"},{"row":453,"row_count":1,"visible":true,"expansion_state":0,"options":{},"document_id":"597FF5A4","chunk_id":"cguejjffnm0mo","chunk_label":"contracts"},{"row":483,"row_count":1,"visible":true,"expansion_state":0,"options":{},"document_id":"597FF5A4","chunk_id":"cv7d7majg0n9t","chunk_label":"salary-overall"},{"row":514,"row_count":1,"visible":true,"expansion_state":0,"options":{},"document_id":"597FF5A4","chunk_id":"cyb1aft1jh5x6","chunk_label":"salary-tables"},{"row":529,"row_count":1,"visible":true,"expansion_state":0,"options":{},"document_id":"597FF5A4","chunk_id":"cam0oaki84rmx","chunk_label":"salary-by-gender"},{"row":542,"row_count":1,"visible":true,"expansion_state":0,"options":{},"document_id":"597FF5A4","chunk_id":"czsibbcderui5","chunk_label":"salary-tt"},{"row":555,"row_count":1,"visible":true,"expansion_state":0,"options":{},"document_id":"597FF5A4","chunk_id":"cinag6z75zw10","chunk_label":"salary-ntt"},{"row":570,"row_count":1,"visible":true,"expansion_state":0,"options":{},"document_id":"597FF5A4","chunk_id":"czhylvtdz177t","chunk_label":"salary-contract"},{"row":596,"row_count":1,"visible":true,"expansion_state":0,"options":{},"document_id":"597FF5A4","chunk_id":"cgo02hysqaf78","chunk_label":"salary-models"},{"row":633,"row_count":1,"visible":true,"expansion_state":0,"options":{},"document_id":"597FF5A4","chunk_id":"cpu6za2elzqen","chunk_label":"pd-funding"},{"row":658,"row_count":1,"visible":true,"expansion_state":0,"options":{},"document_id":"597FF5A4","chunk_id":"cka9qboku7wq1","chunk_label":"salary-funding-sources"},{"row":680,"row_count":1,"visible":true,"expansion_state":0,"options":{},"document_id":"597FF5A4","chunk_id":"ci5t18rph1740","chunk_label":"hours-clinic"},{"row":708,"row_count":1,"visible":true,"expansion_state":0,"options":{},"document_id":"597FF5A4","chunk_id":"c6c2md5nb3dt3","chunk_label":"responsibilities"},{"row":741,"row_count":1,"visible":true,"expansion_state":0,"options":{},"document_id":"597FF5A4","chunk_id":"cdqz2wp06yf8u","chunk_label":"hours-by-activity"},{"row":772,"row_count":1,"visible":true,"expansion_state":0,"options":{},"document_id":"597FF5A4","chunk_id":"cuejzc476x8db","chunk_label":"teaching"},{"row":803,"row_count":1,"visible":true,"expansion_state":0,"options":{},"document_id":"597FF5A4","chunk_id":"cyjq2h6ds1gmv","chunk_label":"clinic-model"},{"row":837,"row_count":1,"visible":true,"expansion_state":0,"options":{},"document_id":"597FF5A4","chunk_id":"cibfpl32qf94w","chunk_label":"trainees-clients"},{"row":847,"row_count":1,"visible":true,"expansion_state":0,"options":{},"document_id":"597FF5A4","chunk_id":"cc4lxdj91m747","chunk_label":"services"},{"row":871,"row_count":1,"visible":true,"expansion_state":0,"options":{},"document_id":"597FF5A4","chunk_id":"cngbtfng81b2a","chunk_label":"client-populations"},{"row":898,"row_count":1,"visible":true,"expansion_state":0,"options":{},"document_id":"597FF5A4","chunk_id":"c7gr8fg08abow","chunk_label":"therapy-services"},{"row":928,"row_count":1,"visible":true,"expansion_state":0,"options":{},"document_id":"597FF5A4","chunk_id":"c15x5vyatqx42","chunk_label":"assessment-services"},{"row":945,"row_count":1,"visible":true,"expansion_state":0,"options":{},"document_id":"597FF5A4","chunk_id":"c7qbjihveww5k","chunk_label":"sliding-scale"},{"row":967,"row_count":1,"visible":true,"expansion_state":0,"options":{},"document_id":"597FF5A4","chunk_id":"cs49tbrksurwo","chunk_label":"revenue"},{"row":1007,"row_count":1,"visible":true,"expansion_state":0,"options":{},"document_id":"597FF5A4","chunk_id":"cf24ryxcf8qur","chunk_label":"fee-structures"},{"row":1017,"row_count":1,"visible":true,"expansion_state":0,"options":{},"document_id":"597FF5A4","chunk_id":"ckwz7tdc27a74","chunk_label":"insurance-billing"},{"row":1040,"row_count":1,"visible":true,"expansion_state":0,"options":{},"document_id":"597FF5A4","chunk_id":"cy2wrbr2t28cg","chunk_label":"revenue-clients"},{"row":1068,"row_count":1,"visible":true,"expansion_state":0,"options":{},"document_id":"597FF5A4","chunk_id":"cwefeip6jaqhl","chunk_label":"clinic-space"},{"row":1088,"row_count":1,"visible":true,"expansion_state":0,"options":{},"document_id":"597FF5A4","chunk_id":"cs0l5blbnzggq","chunk_label":"rooms"},{"row":1108,"row_count":1,"visible":true,"expansion_state":0,"options":{},"document_id":"597FF5A4","chunk_id":"c73ewblyddky1","chunk_label":"supervisors"},{"row":1128,"row_count":1,"visible":true,"expansion_state":0,"options":{},"document_id":"597FF5A4","chunk_id":"cualps0a1xpqh","chunk_label":"max-caseload-details"},{"row":1167,"row_count":1,"visible":true,"expansion_state":0,"options":{},"document_id":"597FF5A4","chunk_id":"cid4uerp41rpj","chunk_label":"staff-details"},{"row":1194,"row_count":1,"visible":true,"expansion_state":0,"options":{},"document_id":"597FF5A4","chunk_id":"ca94i6hanxnyn","chunk_label":"clinic-hours"},{"row":1211,"row_count":1,"visible":true,"expansion_state":0,"options":{},"document_id":"597FF5A4","chunk_id":"crf4bf5rymy2q","chunk_label":"emr"},{"row":1226,"row_count":1,"visible":true,"expansion_state":0,"options":{},"document_id":"597FF5A4","chunk_id":"comejzm0m6z4u","chunk_label":"telehealth"},{"row":1261,"row_count":1,"visible":true,"expansion_state":0,"options":{},"document_id":"597FF5A4","chunk_id":"cz1f4fgreym5n","chunk_label":"telehealth-usage"},{"row":1285,"row_count":1,"visible":true,"expansion_state":0,"options":{},"document_id":"597FF5A4","chunk_id":"cjl1akq26592n","chunk_label":"ai"},{"row":1293,"row_count":1,"visible":true,"expansion_state":0,"options":{},"document_id":"597FF5A4","chunk_id":"c4xk42ozrk9za","chunk_label":"ai-policy"},{"row":1325,"row_count":1,"visible":true,"expansion_state":0,"options":{},"document_id":"597FF5A4","chunk_id":"cact05zgh8038","chunk_label":"rom"},{"row":1361,"row_count":1,"visible":true,"expansion_state":0,"options":{},"document_id":"597FF5A4","chunk_id":"cuom856qtbd11","chunk_label":"dei-activities"},{"row":1376,"row_count":1,"visible":true,"expansion_state":0,"options":{},"document_id":"597FF5A4","chunk_id":"cuatr60rckah5","chunk_label":"research"},{"row":1399,"row_count":1,"visible":true,"expansion_state":0,"options":{},"document_id":"597FF5A4","chunk_id":"chxam5bcyr423","chunk_label":"burnout-single"},{"row":1462,"row_count":1,"visible":true,"expansion_state":0,"options":{},"document_id":"597FF5A4","chunk_id":"crgjms3x7t5so","chunk_label":"burnout-cbi"},{"row":1497,"row_count":1,"visible":true,"expansion_state":0,"options":{},"document_id":"597FF5A4","chunk_id":"chf5kwwvehjh2","chunk_label":"burnout-by-position"},{"row":1503,"row_count":1,"visible":true,"expansion_state":0,"options":{},"document_id":"597FF5A4","chunk_id":"cov2hu2zfwr71","chunk_label":"session"}],"doc_write_time":1770916329,"working_dir":null,"default_chunk_options":{"echo":true,"warning":false,"message":false,"fig.align":"center"},"chunk_rendered_width":551}